IIIFpres/BCP47_tags.py
IIIFpres/BCP47_tags_list.py
IIIFpres/MediaTypes.py
IIIFpres/__init__.py
IIIFpres/createvalidatorstructure.py
IIIFpres/dictmediatype.py
IIIFpres/iiifpapi3.py
IIIFpres/utilities.py
IIIFpres/validatorfunctions.py
IIIFpres/visualization_html.py
IIIFpres/extensions/NavPlace.py
IIIFpres/extensions/__init__.py
tests/__init__.py
tests/integration/__init__.py
tests/integration/tests.py
tests/integration/tests_orjson.py
tests/unit/__init__.py
tests/unit/test.py
pyIIIFpres-0.4.0.dist-info/LICENSE
pyIIIFpres-0.4.0.dist-info/METADATA
pyIIIFpres-0.4.0.dist-info/WHEEL
pyIIIFpres-0.4.0.dist-info/top_level.txt
pyIIIFpres-0.4.0.dist-info/RECORD
