Metadata-Version: 2.1
Name: pyIIIFpres
Version: 0.4.0
Summary: A tool for easing the construction of JSON manifests compliant with IIIF API 3.0.
Home-page: https://github.com/giacomomarchioro/pyIIIFpres
Author: Giacomo Marchioro
Author-email: giacomomarchioro@outlook.com
License: MIT
Classifier: Programming Language :: Python :: 3
Classifier: License :: OSI Approved :: MIT License
Classifier: Operating System :: OS Independent
License-File: LICENSE
